tablecrow/__init__.py
tablecrow/connect.py
tablecrow/utilities.py
tablecrow/tables/__init__.py
tablecrow/tables/base.py
tablecrow/tables/postgres.py
tablecrow/tables/sqlite.py
tablecrow-1.4.7.dist-info/LICENSE
tablecrow-1.4.7.dist-info/METADATA
tablecrow-1.4.7.dist-info/WHEEL
tablecrow-1.4.7.dist-info/top_level.txt
tablecrow-1.4.7.dist-info/RECORD
