Metadata-Version: 2.1
Name: tablecrow
Version: 1.4.7
Summary: abstract interface with remote database table
Author-email: Zach Burnett <zachary.r.burnett@gmail.com>
License: GNU GENERAL PUBLIC LICENSE
Project-URL: repository, https://github.com/zacharyburnett/TableCrow.git
Project-URL: documentation, https://tablecrow.readthedocs.io
Requires-Python: >=3.8
License-File: LICENSE
Requires-Dist: psycopg2-binary
Requires-Dist: pyproj
Requires-Dist: python-dateutil
Requires-Dist: shapely
Requires-Dist: spatialite
Requires-Dist: sshtunnel
Requires-Dist: typepigeon (>=2.0.1)
Provides-Extra: docs
Requires-Dist: dunamai ; extra == 'docs'
Requires-Dist: m2r2 ; extra == 'docs'
Requires-Dist: sphinx ; extra == 'docs'
Requires-Dist: sphinx-rtd-theme ; extra == 'docs'
Provides-Extra: test
Requires-Dist: pytest ; extra == 'test'
